LICENSE
MANIFEST.in
README.md
setup.cfg
setup.py
tap_hubspot/__init__.py
tap_hubspot/schemas/campaigns.json
tap_hubspot/schemas/companies.json
tap_hubspot/schemas/contact_lists.json
tap_hubspot/schemas/contacts.json
tap_hubspot/schemas/contacts_by_company.json
tap_hubspot/schemas/deal_pipelines.json
tap_hubspot/schemas/deals.json
tap_hubspot/schemas/email_events.json
tap_hubspot/schemas/engagements.json
tap_hubspot/schemas/forms.json
tap_hubspot/schemas/owners.json
tap_hubspot/schemas/subscription_changes.json
tap_hubspot/schemas/tickets.json
tap_hubspot/schemas/versions.json
tap_hubspot/schemas/workflows.json
tap_hubspot_spacecowboy.egg-info/PKG-INFO
tap_hubspot_spacecowboy.egg-info/SOURCES.txt
tap_hubspot_spacecowboy.egg-info/dependency_links.txt
tap_hubspot_spacecowboy.egg-info/entry_points.txt
tap_hubspot_spacecowboy.egg-info/requires.txt
tap_hubspot_spacecowboy.egg-info/top_level.txt