Metadata-Version: 2.1
Name: tap-hubspot-spacecowboy
Version: 1.0.0
Summary: Singer.io tap for extracting data from the HubSpot API
Home-page: https://github.com/spacecowboy/tap-hubspot
Author: SpaceCowboy
License: UNKNOWN
Platform: UNKNOWN
Classifier: Programming Language :: Python :: 3 :: Only
Provides-Extra: dev
License-File: LICENSE
